text_based_clusterer/__init__.py
text_based_clusterer/clusterer.py
text_based_clusterer-0.0.2.dist-info/LICENSE
text_based_clusterer-0.0.2.dist-info/METADATA
text_based_clusterer-0.0.2.dist-info/WHEEL
text_based_clusterer-0.0.2.dist-info/top_level.txt
text_based_clusterer-0.0.2.dist-info/RECORD
