Metadata-Version: 2.1
Name: text-based-clusterer
Version: 0.0.2
Summary: A package that clusters python objects based on a chosen string attribute
Home-page: https://github.com/btaguinod/text-based-clusterer
Author: Benedict Taguinod
Author-email: benedict.a.taguinod@gmail.com
License: UNKNOWN
Project-URL: Bug Tracker, https://github.com/btaguinod/text-based-clusterer/issues
Platform: UNKNOWN
Classifier: Programming Language :: Python :: 3
Classifier: License :: OSI Approved :: MIT License
Classifier: Operating System :: OS Independent
Requires-Python: >=3.6
License-File: LICENSE
Requires-Dist: numpy
Requires-Dist: nltk
